README.rst
setup.py
pddsdk/__init__.py
pddsdk/client.py
pddsdk/ddk_app_new_bill_list_get.py
pddsdk/ddk_cms_prom_url_generate.py
pddsdk/ddk_direct_goods_query.py
pddsdk/ddk_goods_detail.py
pddsdk/ddk_goods_pid_generate.py
pddsdk/ddk_goods_pid_query.py
pddsdk/ddk_goods_promotion_url_generate.py
pddsdk/ddk_goods_search.py
pddsdk/ddk_goods_zs_unit_url_gen.py
pddsdk/ddk_order_list_increment_get.py
pddsdk/ddk_rp_prom_url_generate.py
pddsdk/ddk_theme_goods_search.py
pddsdk/ddk_theme_list_get.py
pddsdk/ddk_theme_prom_url_generate.py
pddsdk/ddk_zs_unit_goods_query.py
pddsdk.egg-info/PKG-INFO
pddsdk.egg-info/SOURCES.txt
pddsdk.egg-info/dependency_links.txt
pddsdk.egg-info/requires.txt
pddsdk.egg-info/top_level.txt