Metadata-Version: 1.1
Name: pddsdk
Version: 0.1.15
Summary: an open source api for pingduoduo
Home-page: https://github.com/linzhiming0826/pddsdk
Author: TuoX
Author-email: 120549827@qq.com
License: MIT
Keywords: pddsdk pingduoduo api extend
Platform: UNKNOWN
Classifier: Development Status :: 3 - Alpha
Classifier: Intended Audience :: Developers
Classifier: Topic :: Software Development :: Libraries :: Python Modules
Classifier: License :: OSI Approved :: MIT License
Classifier: Programming Language :: Python :: 3.5
